MANIFEST.in
README.rst
setup.py
jr/__init__.py
jr/cmd.py
jr/common.py
jr/extension.py
jr/filter.py
jr/grammar_parse.py
jr/parser.py
jr/render.py
jr/rule.py
jr.egg-info/PKG-INFO
jr.egg-info/SOURCES.txt
jr.egg-info/dependency_links.txt
jr.egg-info/entry_points.txt
jr.egg-info/requires.txt
jr.egg-info/top_level.txt
test/test_pipeline.py